lib/__init__.py
lib/manhattan_cafe.py
AI_Coach_RLL-1.0.2.dist-info/LICENSE
AI_Coach_RLL-1.0.2.dist-info/METADATA
AI_Coach_RLL-1.0.2.dist-info/WHEEL
AI_Coach_RLL-1.0.2.dist-info/top_level.txt
AI_Coach_RLL-1.0.2.dist-info/RECORD
